irisml/tasks/create_torchvision_model.py
irisml/tasks/create_torchvision_transform.py
irisml/tasks/create_torchvision_transform_v2.py
irisml/tasks/load_torchvision_dataset.py
irisml_tasks_torchvision-0.0.11.dist-info/LICENSE
irisml_tasks_torchvision-0.0.11.dist-info/METADATA
irisml_tasks_torchvision-0.0.11.dist-info/WHEEL
irisml_tasks_torchvision-0.0.11.dist-info/top_level.txt
irisml_tasks_torchvision-0.0.11.dist-info/RECORD
