Metadata-Version: 2.1
Name: irisml-tasks-torchvision
Version: 0.0.11
Summary: Torchvision-related tasks for IrisML
Author: irisdev
License: MIT
Requires-Python: >=3.8
License-File: LICENSE
Requires-Dist: irisml
Requires-Dist: torch
Requires-Dist: torchvision
